gpt3_prompt_to_text/__init__.py
gpt3_prompt_to_text/_version.py
gpt3_prompt_to_text/gpt3_prompt_to_text.py
gpt3_prompt_to_text-1.5.1.dist-info/entry_points.txt
gpt3_prompt_to_text-1.5.1.dist-info/LICENSE.md
gpt3_prompt_to_text-1.5.1.dist-info/WHEEL
gpt3_prompt_to_text-1.5.1.dist-info/METADATA
gpt3_prompt_to_text-1.5.1.dist-info/RECORD
