Metadata-Version: 2.1
Name: gpt3-prompt-to-text
Version: 1.5.1
Summary: A trivial command line tool to invoke OpenAI's completion API
Author-email: Clemens Vasters <clemens@vasters.com>
Requires-Python: >=3.10
Classifier: Programming Language :: Python :: 3
Classifier: License :: OSI Approved :: MIT License
Classifier: Operating System :: OS Independent
Requires-Dist: openai>=0.26.5
